mediabrowser/__init__.py
mediabrowser/constants.py
mediabrowser/forms.py
mediabrowser/models.py
mediabrowser/tests.py
mediabrowser/urls.py
mediabrowser/utils.py
mediabrowser/views.py
mediabrowser/static/mediabrowser/css/mediabrowser.css
mediabrowser/static/mediabrowser/css/smoothness/jquery-ui-1.10.3.custom.min.css
mediabrowser/static/mediabrowser/css/smoothness/images/animated-overlay.gif
mediabrowser/static/mediabrowser/css/smoothness/images/ui-bg_flat_0_aaaaaa_40x100.png
mediabrowser/static/mediabrowser/css/smoothness/images/ui-bg_flat_75_ffffff_40x100.png
mediabrowser/static/mediabrowser/css/smoothness/images/ui-bg_glass_55_fbf9ee_1x400.png
mediabrowser/static/mediabrowser/css/smoothness/images/ui-bg_glass_65_ffffff_1x400.png
mediabrowser/static/mediabrowser/css/smoothness/images/ui-bg_glass_75_dadada_1x400.png
mediabrowser/static/mediabrowser/css/smoothness/images/ui-bg_glass_75_e6e6e6_1x400.png
mediabrowser/static/mediabrowser/css/smoothness/images/ui-bg_glass_95_fef1ec_1x400.png
mediabrowser/static/mediabrowser/css/smoothness/images/ui-bg_highlight-soft_75_cccccc_1x100.png
mediabrowser/static/mediabrowser/css/smoothness/images/ui-icons_222222_256x240.png
mediabrowser/static/mediabrowser/css/smoothness/images/ui-icons_2e83ff_256x240.png
mediabrowser/static/mediabrowser/css/smoothness/images/ui-icons_454545_256x240.png
mediabrowser/static/mediabrowser/css/smoothness/images/ui-icons_888888_256x240.png
mediabrowser/static/mediabrowser/css/smoothness/images/ui-icons_cd0a0a_256x240.png
mediabrowser/static/mediabrowser/img/test.png
mediabrowser/static/mediabrowser/js/jquery-1.9.1.js
mediabrowser/static/mediabrowser/js/jquery-ui-1.10.3.custom.min.js
mediabrowser/static/mediabrowser/js/mediabrowser.js
mediabrowser/templates/mediabrowser/add.html
mediabrowser/templates/mediabrowser/add_success.html
mediabrowser/templates/mediabrowser/base.html
mediabrowser/templates/mediabrowser/list.html
mediabrowser-0.1.1.dist-info/DESCRIPTION.rst
mediabrowser-0.1.1.dist-info/METADATA
mediabrowser-0.1.1.dist-info/RECORD
mediabrowser-0.1.1.dist-info/WHEEL
mediabrowser-0.1.1.dist-info/metadata.json
mediabrowser-0.1.1.dist-info/top_level.txt
